contextooor/.env.example
contextooor/.gitignore
contextooor/__init__.py
contextooor/chainalysis_ofac_api.py
contextooor/eth.py
contextooor_chainalysis-0.0.1.dist-info/WHEEL
contextooor_chainalysis-0.0.1.dist-info/METADATA
contextooor_chainalysis-0.0.1.dist-info/RECORD
