Metadata-Version: 2.1
Name: contextooor-chainalysis
Version: 0.0.1
Summary: "Get contextual information before broadcasting a transaction."
Author-email: David Desjardins <david.thegardens@gmail.com>
Requires-Dist: pytest
Requires-Dist: requests
